deepfinder/__init__.py
deepfinder/bibtex.py
deepfinder/constants.py
deepfinder/icon.png
deepfinder/objects.py
deepfinder/protocols.conf
deepfinder/convert/__init__.py
deepfinder/protocols/__init__.py
deepfinder/protocols/protocol_annotation.py
deepfinder/protocols/protocol_base.py
deepfinder/protocols/protocol_cluster.py
deepfinder/protocols/protocol_import_coordinates.py
deepfinder/protocols/protocol_load_training_model.py
deepfinder/protocols/protocol_segment.py
deepfinder/protocols/protocol_target_generation.py
deepfinder/protocols/protocol_train.py
deepfinder/templates/deepfinder-workflow.json.template
deepfinder/tests/__init__.py
deepfinder/tests/test_deepfinder.py
deepfinder/viewers/__init__.py
deepfinder/viewers/learning_curves_viewer.py
deepfinder/viewers/particle_annotator_tomo_viewer.py
deepfinder/viewers/particle_annotator_tree.py
deepfinder/viewers/tomograms_tomomasks_viewer.py
scipion_em_deepfinder-3.2.1.dist-info/LICENSE
scipion_em_deepfinder-3.2.1.dist-info/METADATA
scipion_em_deepfinder-3.2.1.dist-info/WHEEL
scipion_em_deepfinder-3.2.1.dist-info/entry_points.txt
scipion_em_deepfinder-3.2.1.dist-info/top_level.txt
scipion_em_deepfinder-3.2.1.dist-info/RECORD
